{
    "keep": {
        "days": true,
        "amount": 14
    },
    "auditLog": "E:\\Programming Hero Next Level Batch 1\\University management auth service\\logs\\winston\\errors\\.cda1d450a5a76b2376e6152acae999ddce606eff-audit.json",
    "files": [
        {
            "date": 1687887110377,
            "name": "E:\\Programming Hero Next Level Batch 1\\University management auth service\\logs\\winston\\errors\\PH-UMAS-2023-27-06-23-error.log",
            "hash": "6518367a7276e4d68ceade31da84551aff5538bb2de18b98c2ce73c81d1d45da"
        },
        {
            "date": 1687888822389,
            "name": "E:\\Programming Hero Next Level Batch 1\\University management auth service\\logs\\winston\\errors\\PH-UMAS-2023-28-06-00-error.log",
            "hash": "84a2ad7d84937dbf14faadbd0e5a7b7e2f2a63ba956b400070d6f5409dc5e43e"
        },
        {
            "date": 1687894607141,
            "name": "E:\\Programming Hero Next Level Batch 1\\University management auth service\\logs\\winston\\errors\\PH-UMAS-2023-28-06-01-error.log",
            "hash": "229c72ed916f3cbd3d44693c3ea5def5a4c6a9cf2c5869ba318f84bc8ba48a66"
        },
        {
            "date": 1687896084085,
            "name": "E:\\Programming Hero Next Level Batch 1\\University management auth service\\logs\\winston\\errors\\PH-UMAS-2023-28-06-02-error.log",
            "hash": "644908d3901c5e22baacda8665e87e292902b58f17947c82481b30df12a9427f"
        },
        {
            "date": 1688327284866,
            "name": "E:\\Programming Hero Next Level Batch 1\\University management auth service\\logs\\winston\\errors\\PH-UMAS-2023-03-07-01-error.log",
            "hash": "1d4d0a9e74c2967e46e9cceca5971be79115bd55e37f5ac80f19aac90b8669bb"
        },
        {
            "date": 1688328646772,
            "name": "E:\\Programming Hero Next Level Batch 1\\University management auth service\\logs\\winston\\errors\\PH-UMAS-2023-03-07-02-error.log",
            "hash": "8c6fcff36ed8ad0d27403f1a9999c56161caaf1fd7b1599b8a9d8cb9bb1efcf7"
        },
        {
            "date": 1688331710365,
            "name": "E:\\Programming Hero Next Level Batch 1\\University management auth service\\logs\\winston\\errors\\PH-UMAS-2023-03-07-03-error.log",
            "hash": "a7bd9d4a31da96bc7b46a2e9bc89af351db0f05e3786934c5a1ee1a521dce447"
        },
        {
            "date": 1688371278695,
            "name": "E:\\Programming Hero Next Level Batch 1\\University management auth service\\logs\\winston\\errors\\PH-UMAS-2023-03-07-14-error.log",
            "hash": "2fb5e58d2eec034d12c59f9e6340b0daf620f63a46c3e168da94fb04609a395f"
        },
        {
            "date": 1688375643131,
            "name": "E:\\Programming Hero Next Level Batch 1\\University management auth service\\logs\\winston\\errors\\PH-UMAS-2023-03-07-15-error.log",
            "hash": "2dde68d00f49b506eed97f3cc92bb12356f913f089965651d2e15d4fb1b9466d"
        },
        {
            "date": 1688399100286,
            "name": "E:\\Programming Hero Next Level Batch 1\\University management auth service\\logs\\winston\\errors\\PH-UMAS-2023-03-07-21-error.log",
            "hash": "2efe2992e35cb17549a543218bf731dfefaeac94669f8fb58f87ec0474dac1b0"
        },
        {
            "date": 1688400134970,
            "name": "E:\\Programming Hero Next Level Batch 1\\University management auth service\\logs\\winston\\errors\\PH-UMAS-2023-03-07-22-error.log",
            "hash": "ddebe92e7bdb3c1b364d085ea5de3f4d2e41e5373b45ea460b295af2a869c90c"
        },
        {
            "date": 1688406010753,
            "name": "E:\\Programming Hero Next Level Batch 1\\University management auth service\\logs\\winston\\errors\\PH-UMAS-2023-03-07-23-error.log",
            "hash": "ed9a7422efa6028212ded3084f7f89a657f51db8902cc9ef9e40abe23461d0d2"
        },
        {
            "date": 1688487298590,
            "name": "E:\\Programming Hero Next Level Batch 1\\University management auth service\\logs\\winston\\errors\\PH-UMAS-2023-04-07-22-error.log",
            "hash": "9fc3321db1634ea594567484955257ffea641b7c985d2c86b60df85d222c088c"
        },
        {
            "date": 1688490189999,
            "name": "E:\\Programming Hero Next Level Batch 1\\University management auth service\\logs\\winston\\errors\\PH-UMAS-2023-04-07-23-error.log",
            "hash": "7f0e9293740ea9d8544e1ae26de18ba12ab2fb58f04644501888e25fb26e588b"
        },
        {
            "date": 1688495238804,
            "name": "E:\\Programming Hero Next Level Batch 1\\University management auth service\\logs\\winston\\errors\\PH-UMAS-2023-05-07-00-error.log",
            "hash": "5ad975ac1c75174cc42858447892285b4d140a1c00a98a4e58e1d9acb458e404"
        },
        {
            "date": 1688497675097,
            "name": "E:\\Programming Hero Next Level Batch 1\\University management auth service\\logs\\winston\\errors\\PH-UMAS-2023-05-07-01-error.log",
            "hash": "09e6e29c693cabf7a99e02fc7b74712026eaaca89f42d0728cccf4d86e233727"
        },
        {
            "date": 1688500919607,
            "name": "E:\\Programming Hero Next Level Batch 1\\University management auth service\\logs\\winston\\errors\\PH-UMAS-2023-05-07-02-error.log",
            "hash": "b74f508a6b339a2dfaa53db70fb7a8cac558100ee7bf046f906728702e722838"
        },
        {
            "date": 1688547881899,
            "name": "E:\\Programming Hero Next Level Batch 1\\University management auth service\\logs\\winston\\errors\\PH-UMAS-2023-05-07-15-error.log",
            "hash": "ec7eab72114d8ad820533ed674a6e69696b7a7c2d761943a168256e1d273db3f"
        },
        {
            "date": 1688551430988,
            "name": "E:\\Programming Hero Next Level Batch 1\\University management auth service\\logs\\winston\\errors\\PH-UMAS-2023-05-07-16-error.log",
            "hash": "336163b29f60a0a2936eaa8a75fdf8ba912523b5676e58d14a9225f85e0ca95c"
        },
        {
            "date": 1688633893545,
            "name": "E:\\Programming Hero Next Level Batch 1\\University management auth service\\logs\\winston\\errors\\PH-UMAS-2023-06-07-14-error.log",
            "hash": "405fffb3127abe2e3c69c8c8803a461cee2034b68d8cdca182f24c44843d2918"
        },
        {
            "date": 1688651062260,
            "name": "E:\\Programming Hero Next Level Batch 1\\University management auth service\\logs\\winston\\errors\\PH-UMAS-2023-06-07-19-error.log",
            "hash": "79c41b4b75eb933b2e0776a3f8f3f8e5f68069e7576b7b7be9941f2bf20340f3"
        },
        {
            "date": 1688652063953,
            "name": "E:\\Programming Hero Next Level Batch 1\\University management auth service\\logs\\winston\\errors\\PH-UMAS-2023-06-07-20-error.log",
            "hash": "4ce9944b671d37172ddbf1ef236ad54bb1f04c3b8176cadf19abec9f3c2a53b3"
        },
        {
            "date": 1688674546611,
            "name": "E:\\Programming Hero Next Level Batch 1\\University management auth service\\logs\\winston\\errors\\PH-UMAS-2023-07-07-02-error.log",
            "hash": "861a1377ab4c21cb6001faa90659de810b19de717c386f8fbbacc2676c47e3a7"
        },
        {
            "date": 1688677517717,
            "name": "E:\\Programming Hero Next Level Batch 1\\University management auth service\\logs\\winston\\errors\\PH-UMAS-2023-07-07-03-error.log",
            "hash": "7d81dcffac915b800fec555fccd1093979560c54e7a98633732e75047dddc0d3"
        },
        {
            "date": 1688727628196,
            "name": "E:\\Programming Hero Next Level Batch 1\\University management auth service\\logs\\winston\\errors\\PH-UMAS-2023-07-07-17-error.log",
            "hash": "aac7afb3588b2796f287d33801ee5cb854b98ba2f77a13ea1cbaaebcbd1c9f3f"
        },
        {
            "date": 1688731505877,
            "name": "E:\\Programming Hero Next Level Batch 1\\University management auth service\\logs\\winston\\errors\\PH-UMAS-2023-07-07-18-error.log",
            "hash": "0378db35a81f0ceaf63480a22d8f774c7f69a857c4b15752801f5eecab96656a"
        },
        {
            "date": 1688747259012,
            "name": "E:\\Programming Hero Next Level Batch 1\\University management auth service\\logs\\winston\\errors\\PH-UMAS-2023-07-07-22-error.log",
            "hash": "4357478187a2f8b2d6b1b889960c82c2a09bb8d04dd7a5d643a154b6d7048492"
        },
        {
            "date": 1688749590300,
            "name": "E:\\Programming Hero Next Level Batch 1\\University management auth service\\logs\\winston\\errors\\PH-UMAS-2023-07-07-23-error.log",
            "hash": "d214895acba33e5802eae54f7f3b0ad2fa4908cae2751399fc0b7f5834d529ad"
        },
        {
            "date": 1688753369319,
            "name": "E:\\Programming Hero Next Level Batch 1\\University management auth service\\logs\\winston\\errors\\PH-UMAS-2023-08-07-00-error.log",
            "hash": "c4937f603910be82c47d2a724c8e174cdd9d8ad14281085aa8308da207ad4afa"
        },
        {
            "date": 1689023830754,
            "name": "E:\\Programming Hero Next Level Batch 1\\University management auth service\\logs\\winston\\errors\\PH-UMAS-2023-11-07-03-error.log",
            "hash": "7ceb0f0bb41d60899881e59efc50f051dbfd63753a99a5ed51cb9cec434e32d5"
        },
        {
            "date": 1689060294343,
            "name": "E:\\Programming Hero Next Level Batch 1\\University management auth service\\logs\\winston\\errors\\PH-UMAS-2023-11-07-13-error.log",
            "hash": "98b116177aecaefb74ac7e119369b1216e981948ba2b2bf95f3e5d78ef3bf782"
        },
        {
            "date": 1689062586449,
            "name": "E:\\Programming Hero Next Level Batch 1\\University management auth service\\logs\\winston\\errors\\PH-UMAS-2023-11-07-14-error.log",
            "hash": "b0ce4cc6814bad5dda4ec41722cf25720693fa024a11cc5ba9db8549f292d1d0"
        },
        {
            "date": 1689066256452,
            "name": "E:\\Programming Hero Next Level Batch 1\\University management auth service\\logs\\winston\\errors\\PH-UMAS-2023-11-07-15-error.log",
            "hash": "617596d0859b2c4a6bef0f209406aaa6f88482a5b534b2bc8747fbee46c66a3d"
        },
        {
            "date": 1689069943702,
            "name": "E:\\Programming Hero Next Level Batch 1\\University management auth service\\logs\\winston\\errors\\PH-UMAS-2023-11-07-16-error.log",
            "hash": "89d656b517bf5ddb54581bc3d4d7b0e27faf7f6b32fdcbadd15c635113b0dd52"
        },
        {
            "date": 1689084441533,
            "name": "E:\\Programming Hero Next Level Batch 1\\University management auth service\\logs\\winston\\errors\\PH-UMAS-2023-11-07-20-error.log",
            "hash": "79d2d59a22f4e95081f7b977f7ad02aaf10ad1d0a4a3633eb78456c0991130b5"
        },
        {
            "date": 1689087807695,
            "name": "E:\\Programming Hero Next Level Batch 1\\University management auth service\\logs\\winston\\errors\\PH-UMAS-2023-11-07-21-error.log",
            "hash": "d51665edb0b4a485179de7eac13b54eedb19aacd439d39d38da5ed9fd1283525"
        },
        {
            "date": 1689091369210,
            "name": "E:\\Programming Hero Next Level Batch 1\\University management auth service\\logs\\winston\\errors\\PH-UMAS-2023-11-07-22-error.log",
            "hash": "86c71f40c65a7078da78c490d8ea406b6078ebfefb23105b91734857d741bd61"
        }
    ],
    "hashType": "sha256"
}